Metadata-Version: 2.1
Name: tcl-magic
Version: 0.0.5
Summary: An IPython extension for Tcl.
Home-page: https://github.com/hieberst/tcl-magic
Author: Steffen Hieber
Author-email: hieberst@gmx.de
License: MIT
Keywords: ipython notebook tcl
Platform: any
Classifier: Development Status :: 4 - Beta
Classifier: Environment :: Web Environment
Classifier: Framework :: IPython
Classifier: Framework :: Jupyter
Classifier: Intended Audience :: Developers
Classifier: License :: OSI Approved :: MIT License
Classifier: Operating System :: OS Independent
Classifier: Programming Language :: Python
Classifier: Programming Language :: Tcl
Classifier: Topic :: Software Development :: Libraries :: Python Modules
